MANIFEST.in
setup.py
bootstrap_crud/__init__.py
bootstrap_crud/celldesigner/__init__.py
bootstrap_crud/celldesigner/designer.py
bootstrap_crud/static/css/boostrap-crud.css~
bootstrap_crud/static/css/bootsrap-crud.css~
bootstrap_crud/static/css/bootstrap-crud.css
bootstrap_crud/static/css/bootstrap-crud.css~
bootstrap_crud/templates/celldesigner/bold.html
bootstrap_crud/templates/celldesigner/italic.html
bootstrap_crud/templates/crud/crud_edit.html
bootstrap_crud/templates/crud/crud_error.html
bootstrap_crud/templates/crud/crud_list.html
bootstrap_crud/templates/crud/crud_remove.html
bootstrap_crud/templates/crud/crud_success.html
bootstrap_crud/templatetags/__init__.py
bootstrap_crud/templatetags/crud_renderer.py
django_bootstrap_crud.egg-info/PKG-INFO
django_bootstrap_crud.egg-info/SOURCES.txt
django_bootstrap_crud.egg-info/dependency_links.txt
django_bootstrap_crud.egg-info/top_level.txt