Metadata-Version: 1.1
Name: django-bootstrap-crud
Version: 0.1.0
Summary: CRUD support for Django-Bootstrap projects
Home-page: https://github.com/garciaguimeras/django-bootstrap-crud
Author: Noel Garcia Guimeras
Author-email: garcia.guimeras@gmail.com
License: Apache License 2.0
Platform: UNKNOWN
Classifier: Development Status :: 3 - Alpha
Classifier: Intended Audience :: Developers
Classifier: License :: OSI Approved :: Apache Software License
Classifier: Programming Language :: Python
Classifier: Operating System :: OS Independent
Classifier: Topic :: Software Development :: Libraries
Classifier: Topic :: Utilities
Classifier: Environment :: Web Environment
Classifier: Framework :: Django
